pinyin_kana/__init__.py
pinyin_kana/pinyin_converter.py
pinyin_kana/pinyin_dicts.py
pinyin_kana-0.0.6.dist-info/LICENSE
pinyin_kana-0.0.6.dist-info/METADATA
pinyin_kana-0.0.6.dist-info/WHEEL
pinyin_kana-0.0.6.dist-info/top_level.txt
pinyin_kana-0.0.6.dist-info/RECORD
