Metadata-Version: 2.1
Name: pinyin_kana
Version: 0.0.6
Summary: The `chinese-pronounce-in-kana` library is designed to convert Chinese text into Japanese Katakana characters based on their pronunciation.
Author-email: Ryan Cheng <m61216051116@gmail.com>
License: MIT
Project-URL: Homepage, https://github.com/RUI-LONG/Python-Pinyin-Kana
Keywords: pinyin,pronounce,kana,voice
Classifier: Development Status :: 5 - Production/Stable
Classifier: Natural Language :: English
Classifier: Operating System :: POSIX
Classifier: Operating System :: Microsoft :: Windows
Classifier: Programming Language :: Python :: 3
Classifier: Programming Language :: Python :: 3.7
Classifier: Programming Language :: Python :: 3.8
Classifier: Programming Language :: Python :: 3.9
Classifier: Topic :: Communications
Classifier: Topic :: Software Development :: Libraries
Classifier: Topic :: Software Development :: Libraries :: Python Modules
Requires-Python: >=3.7
License-File: LICENSE
Requires-Dist: pypinyin >=0.42
